floating_hippo/__init__.py
floating_hippo/examples.py
floating_hippo/sim.py
floating_hippo/utils.py
floating_hippo-0.0.10.dist-info/LICENSE
floating_hippo-0.0.10.dist-info/METADATA
floating_hippo-0.0.10.dist-info/WHEEL
floating_hippo-0.0.10.dist-info/top_level.txt
floating_hippo-0.0.10.dist-info/RECORD
